bitpy/__init__.py
bitpy/exceptions.py
bitpy/rest_api.py
bitpy/ws_api.py
bitpy/clients/account.py
bitpy/clients/base_client.py
bitpy/clients/market.py
bitpy/clients/position.py
bitpy/clients/ws.py
bitpy/models/account.py
bitpy/models/base.py
bitpy/models/login.py
bitpy/models/market.py
bitpy/models/position.py
bitpy/utils/log_manager.py
bitpy/utils/request_handler.py
bitget_python-1.0.4.dist-info/LICENSE
bitget_python-1.0.4.dist-info/METADATA
bitget_python-1.0.4.dist-info/WHEEL
bitget_python-1.0.4.dist-info/top_level.txt
bitget_python-1.0.4.dist-info/RECORD
