Metadata-Version: 2.1
Name: bitget-python
Version: 1.0.4
Summary: A Python client for the Bitget API with comprehensive position management
Author: Tentoxa
License: MIT
Project-URL: Homepage, https://github.com/Tentoxa/bitpy
Project-URL: Repository, https://github.com/Tentoxa/bitpy
Project-URL: Documentation, https://github.com/Tentoxa/bitpy#readme
Keywords: bitget,api,trading,cryptocurrency
Classifier: Development Status :: 5 - Production/Stable
Classifier: Intended Audience :: Developers
Classifier: License :: OSI Approved :: MIT License
Classifier: Programming Language :: Python :: 3
Classifier: Programming Language :: Python :: 3.9
Classifier: Programming Language :: Python :: 3.10
Classifier: Programming Language :: Python :: 3.11
Classifier: Topic :: Software Development :: Libraries :: Python Modules
Requires-Python: >=3.9
License-File: LICENSE
Requires-Dist: requests>=2.32.2
Requires-Dist: websockets>=14.1
